{"version": 0.6, "generator": "Overpass API 0.7.62.5 1bd436f1", "osm3s": {"timestamp_osm_base": "2025-04-18T11:20:38Z", "copyright": "The data included in this document is from www.openstreetmap.org. The data is made available under ODbL."}, "elements": [{"type": "node", "id": 5633606734, "lat": 38.7452986, "lon": -90.561747, "tags": {"addr:city": "Saint Peters", "addr:housenumber": "1120", "addr:postcode": "63303", "addr:street": "Jungs Station Road"}}, {"type": "node", "id": 5633606769, "lat": 38.7481133, "lon": -90.5626604, "tags": {"addr:city": "Saint Peters", "addr:housenumber": "1315", "addr:postcode": "63303", "addr:street": "Jungs Station Road"}}, {"type": "node", "id": 6402067945, "lat": 38.7445432, "lon": -90.5609355, "tags": {"addr:city": "Saint Peters", "addr:housenumber": "1124", "addr:postcode": "63303", "addr:street": "Wild Plum Drive", "source:addr": "https://gis.sccmo.opendata.arcgis.com/ (2018)"}}, {"type": "node", "id": 6402067946, "lat": 38.7445815, "lon": -90.5614006, "tags": {"addr:city": "Saint Peters", "addr:housenumber": "1125", "addr:postcode": "63303", "addr:street": "Wild Plum Drive", "source:addr": "https://gis.sccmo.opendata.arcgis.com/ (2018)"}}, {"type": "node", "id": 6402067949, "lat": 38.7444639, "lon": -90.5614054, "tags": {"addr:city": "Saint Peters", "addr:housenumber": "1123", "addr:postcode": "63303", "addr:street": "Wild Plum Drive", "source:addr": "https://gis.sccmo.opendata.arcgis.com/ (2018)"}}, {"type": "node", "id": 6402068004, "lat": 38.7444467, "lon": -90.5606355, "tags": {"addr:city": "Saint Peters", "addr:housenumber": "2802", "addr:postcode": "63303", "addr:street": "Plum Leaf Circle", "source:addr": "https://gis.sccmo.opendata.arcgis.com/ (2018)"}}, {"type": "node", "id": 6402068007, "lat": 38.7444386, "lon": -90.5600226, "tags": {"addr:city": "Saint Peters", "addr:housenumber": "2810", "addr:postcode": "63303", "addr:street": "Plum Leaf Circle", "source:addr": "https://gis.sccmo.opendata.arcgis.com/ (2018)"}}, {"type": "node", "id": 6402068009, "lat": 38.7444397, "lon": -90.5601586, "tags": {"addr:city": "Saint Peters", "addr:housenumber": "2808", "addr:postcode": "63303", "addr:street": "Plum Leaf Circle", "source:addr": "https://gis.sccmo.opendata.arcgis.com/ (2018)"}}, {"type": "node", "id": 6402068028, "lat": 38.7444541, "lon": -90.5605108, "tags": {"addr:city": "Saint Peters", "addr:housenumber": "2804", "addr:postcode": "63303", "addr:street": "Plum Leaf Circle", "source:addr": "https://gis.sccmo.opendata.arcgis.com/ (2018)"}}, {"type": "node", "id": 6402068046, "lat": 38.7444422, "lon": -90.5603265, "tags": {"addr:city": "Saint Peters", "addr:housenumber": "2806", "addr:postcode": "63303", "addr:street": "Plum Leaf Circle", "source:addr": "https://gis.sccmo.opendata.arcgis.com/ (2018)"}}, {"type": "node", "id": 6402068357, "lat": 38.7453202, "lon": -90.5576972, "tags": {"addr:city": "Saint Peters", "addr:housenumber": "1272", "addr:postcode": "63303", "addr:street": "Triangle Drive", "source:addr": "https://gis.sccmo.opendata.arcgis.com/ (2018)"}}, {"type": "node", "id": 6402068358, "lat": 38.7452487, "lon": -90.5575583, "tags": {"addr:city": "Saint Peters", "addr:housenumber": "1274", "addr:postcode": "63303", "addr:street": "Triangle Drive", "source:addr": "https://gis.sccmo.opendata.arcgis.com/ (2018)"}}, {"type": "node", "id": 6402068359, "lat": 38.74518, "lon": -90.5576313, "tags": {"addr:city": "Saint Peters", "addr:housenumber": "1270", "addr:postcode": "63303", "addr:street": "Triangle Drive", "source:addr": "https://gis.sccmo.opendata.arcgis.com/ (2018)"}}, {"type": "node", "id": 6402068360, "lat": 38.7458543, "lon": -90.5590563, "tags": {"addr:city": "Saint Peters", "addr:housenumber": "1452", "addr:postcode": "63303", "addr:street": "Triangle Drive", "source:addr": "https://gis.sccmo.opendata.arcgis.com/ (2018)"}}, {"type": "node", "id": 6402068361, "lat": 38.7458086, "lon": -90.5589613, "tags": {"addr:city": "Saint Peters", "addr:housenumber": "1454", "addr:postcode": "63303", "addr:street": "Triangle Drive", "source:addr": "https://gis.sccmo.opendata.arcgis.com/ (2018)"}}, {"type": "node", "id": 6402068362, "lat": 38.7450771, "lon": -90.5575144, "tags": {"addr:city": "Saint Peters", "addr:housenumber": "1288", "addr:postcode": "63303", "addr:street": "Triangle Drive", "source:addr": "https://gis.sccmo.opendata.arcgis.com/ (2018)"}}, {"type": "node", "id": 6402068363, "lat": 38.7456453, "lon": -90.5594835, "tags": {"addr:city": "Saint Peters", "addr:housenumber": "1428", "addr:postcode": "63303", "addr:street": "Triangle Drive", "source:addr": "https://gis.sccmo.opendata.arcgis.com/ (2018)"}}, {"type": "node", "id": 6402068364, "lat": 38.7460722, "lon": -90.5580557, "tags": {"addr:city": "Saint Peters", "addr:housenumber": "1224", "addr:postcode": "63303", "addr:street": "Triangle Drive", "source:addr": "https://gis.sccmo.opendata.arcgis.com/ (2018)"}}, {"type": "node", "id": 6402068365, "lat": 38.7456968, "lon": -90.5595675, "tags": {"addr:city": "Saint Peters", "addr:housenumber": "1432", "addr:postcode": "63303", "addr:street": "Triangle Drive", "source:addr": "https://gis.sccmo.opendata.arcgis.com/ (2018)"}}, {"type": "node", "id": 6402068366, "lat": 38.7457483, "lon": -90.5593959, "tags": {"addr:city": "Saint Peters", "addr:housenumber": "1422", "addr:postcode": "63303", "addr:street": "Triangle Drive", "source:addr": "https://gis.sccmo.opendata.arcgis.com/ (2018)"}}, {"type": "node", "id": 6402068367, "lat": 38.7459951, "lon": -90.5579424, "tags": {"addr:city": "Saint Peters", "addr:housenumber": "1226", "addr:postcode": "63303", "addr:street": "Triangle Drive", "source:addr": "https://gis.sccmo.opendata.arcgis.com/ (2018)"}}, {"type": "node", "id": 6402068368, "lat": 38.7448266, "lon": -90.5602032, "tags": {"addr:city": "Saint Peters", "addr:housenumber": "1900", "addr:postcode": "63303", "addr:street": "Triangle Drive", "source:addr": "https://gis.sccmo.opendata.arcgis.com/ (2018)"}}, {"type": "node", "id": 6402068369, "lat": 38.7458112, "lon": -90.5594909, "tags": {"addr:city": "Saint Peters", "addr:housenumber": "1434", "addr:postcode": "63303", "addr:street": "Triangle Drive", "source:addr": "https://gis.sccmo.opendata.arcgis.com/ (2018)"}}, {"type": "node", "id": 6402068370, "lat": 38.7459063, "lon": -90.5580373, "tags": {"addr:city": "Saint Peters", "addr:housenumber": "1222", "addr:postcode": "63303", "addr:street": "Triangle Drive", "source:addr": "https://gis.sccmo.opendata.arcgis.com/ (2018)"}}, {"type": "node", "id": 6402068371, "lat": 38.7457512, "lon": -90.5593959, "tags": {"addr:city": "Saint Peters", "addr:housenumber": "1430", "addr:postcode": "63303", "addr:street": "Triangle Drive", "source:addr": "https://gis.sccmo.opendata.arcgis.com/ (2018)"}}, {"type": "node", "id": 6402068372, "lat": 38.744948, "lon": -90.5602152, "tags": {"addr:city": "Saint Peters", "addr:housenumber": "1800", "addr:postcode": "63303", "addr:street": "Triangle Drive", "source:addr": "https://gis.sccmo.opendata.arcgis.com/ (2018)"}}, {"type": "node", "id": 6402068373, "lat": 38.7453194, "lon": -90.5592714, "tags": {"addr:city": "Saint Peters", "addr:housenumber": "1382", "addr:postcode": "63303", "addr:street": "Triangle Drive", "source:addr": "https://gis.sccmo.opendata.arcgis.com/ (2018)"}}, {"type": "node", "id": 6402068374, "lat": 38.7459949, "lon": -90.5581616, "tags": {"addr:city": "Saint Peters", "addr:housenumber": "1228", "addr:postcode": "63303", "addr:street": "Triangle Drive", "source:addr": "https://gis.sccmo.opendata.arcgis.com/ (2018)"}}, {"type": "node", "id": 6402068375, "lat": 38.7453165, "lon": -90.5592714, "tags": {"addr:city": "Saint Peters", "addr:housenumber": "1390", "addr:postcode": "63303", "addr:street": "Triangle Drive", "source:addr": "https://gis.sccmo.opendata.arcgis.com/ (2018)"}}, {"type": "node", "id": 6402068376, "lat": 38.7452621, "lon": -90.5593151, "tags": {"addr:city": "Saint Peters", "addr:housenumber": "1394", "addr:postcode": "63303", "addr:street": "Triangle Drive", "source:addr": "https://gis.sccmo.opendata.arcgis.com/ (2018)"}}, {"type": "node", "id": 6402068377, "lat": 38.7450928, "lon": -90.5601932, "tags": {"addr:city": "Saint Peters", "addr:housenumber": "1700", "addr:postcode": "63303", "addr:street": "Triangle Drive", "source:addr": "https://gis.sccmo.opendata.arcgis.com/ (2018)"}}, {"type": "node", "id": 6402068378, "lat": 38.7460694, "lon": -90.5580521, "tags": {"addr:city": "Saint Peters", "addr:housenumber": "1232", "addr:postcode": "63303", "addr:street": "Triangle Drive", "source:addr": "https://gis.sccmo.opendata.arcgis.com/ (2018)"}}, {"type": "node", "id": 6402068379, "lat": 38.7459922, "lon": -90.5579388, "tags": {"addr:city": "Saint Peters", "addr:housenumber": "1234", "addr:postcode": "63303", "addr:street": "Triangle Drive", "source:addr": "https://gis.sccmo.opendata.arcgis.com/ (2018)"}}, {"type": "node", "id": 6402068380, "lat": 38.7452622, "lon": -90.5591471, "tags": {"addr:city": "Saint Peters", "addr:housenumber": "1380", "addr:postcode": "63303", "addr:street": "Triangle Drive", "source:addr": "https://gis.sccmo.opendata.arcgis.com/ (2018)"}}, {"type": "node", "id": 6402068381, "lat": 38.7459035, "lon": -90.5580337, "tags": {"addr:city": "Saint Peters", "addr:housenumber": "1230", "addr:postcode": "63303", "addr:street": "Triangle Drive", "source:addr": "https://gis.sccmo.opendata.arcgis.com/ (2018)"}}, {"type": "node", "id": 6402068382, "lat": 38.7451736, "lon": -90.5602037, "tags": {"addr:city": "Saint Peters", "addr:housenumber": "1600", "addr:postcode": "63303", "addr:street": "Triangle Drive", "source:addr": "https://gis.sccmo.opendata.arcgis.com/ (2018)"}}, {"type": "node", "id": 6402068383, "lat": 38.7454172, "lon": -90.5580625, "tags": {"addr:city": "Saint Peters", "addr:housenumber": "1248", "addr:postcode": "63303", "addr:street": "Triangle Drive", "source:addr": "https://gis.sccmo.opendata.arcgis.com/ (2018)"}}, {"type": "node", "id": 6402068384, "lat": 38.7452622, "lon": -90.5591508, "tags": {"addr:city": "Saint Peters", "addr:housenumber": "1388", "addr:postcode": "63303", "addr:street": "Triangle Drive", "source:addr": "https://gis.sccmo.opendata.arcgis.com/ (2018)"}}, {"type": "node", "id": 6402068385, "lat": 38.7452779, "lon": -90.5601961, "tags": {"addr:city": "Saint Peters", "addr:housenumber": "1500", "addr:postcode": "63303", "addr:street": "Triangle Drive", "source:addr": "https://gis.sccmo.opendata.arcgis.com/ (2018)"}}, {"type": "node", "id": 6402068386, "lat": 38.7451964, "lon": -90.5592128, "tags": {"addr:city": "Saint Peters", "addr:housenumber": "1392", "addr:postcode": "63303", "addr:street": "Triangle Drive", "source:addr": "https://gis.sccmo.opendata.arcgis.com/ (2018)"}}, {"type": "node", "id": 6402068387, "lat": 38.7457256, "lon": -90.5590416, "tags": {"addr:city": "Saint Peters", "addr:housenumber": "1450", "addr:postcode": "63303", "addr:street": "Triangle Drive", "source:addr": "https://gis.sccmo.opendata.arcgis.com/ (2018)"}}, {"type": "node", "id": 6402068388, "lat": 38.7459747, "lon": -90.5585451, "tags": {"addr:city": "Saint Peters", "addr:housenumber": "1212", "addr:postcode": "63303", "addr:street": "Triangle Drive", "source:addr": "https://gis.sccmo.opendata.arcgis.com/ (2018)"}}, {"type": "node", "id": 6402068389, "lat": 38.7457771, "lon": -90.5591147, "tags": {"addr:city": "Saint Peters", "addr:housenumber": "1448", "addr:postcode": "63303", "addr:street": "Triangle Drive", "source:addr": "https://gis.sccmo.opendata.arcgis.com/ (2018)"}}, {"type": "node", "id": 6402068390, "lat": 38.7460376, "lon": -90.558662, "tags": {"addr:city": "Saint Peters", "addr:housenumber": "1216", "addr:postcode": "63303", "addr:street": "Triangle Drive", "source:addr": "https://gis.sccmo.opendata.arcgis.com/ (2018)"}}, {"type": "node", "id": 6402068391, "lat": 38.7454885, "lon": -90.5585191, "tags": {"addr:city": "Saint Peters", "addr:housenumber": "1333", "addr:postcode": "63303", "addr:street": "Triangle Drive", "source:addr": "https://gis.sccmo.opendata.arcgis.com/ (2018)"}}, {"type": "node", "id": 6402068392, "lat": 38.7461492, "lon": -90.5585598, "tags": {"addr:city": "Saint Peters", "addr:housenumber": "1218", "addr:postcode": "63303", "addr:street": "Triangle Drive", "source:addr": "https://gis.sccmo.opendata.arcgis.com/ (2018)"}}, {"type": "node", "id": 6402068393, "lat": 38.7455457, "lon": -90.5586068, "tags": {"addr:city": "Saint Peters", "addr:housenumber": "1329", "addr:postcode": "63303", "addr:street": "Triangle Drive", "source:addr": "https://gis.sccmo.opendata.arcgis.com/ (2018)"}}, {"type": "node", "id": 6402068394, "lat": 38.7460892, "lon": -90.5584466, "tags": {"addr:city": "Saint Peters", "addr:housenumber": "1214", "addr:postcode": "63303", "addr:street": "Triangle Drive", "source:addr": "https://gis.sccmo.opendata.arcgis.com/ (2018)"}}, {"type": "node", "id": 6402068395, "lat": 38.7454369, "lon": -90.5587126, "tags": {"addr:city": "Saint Peters", "addr:housenumber": "1331", "addr:postcode": "63303", "addr:street": "Triangle Drive", "source:addr": "https://gis.sccmo.opendata.arcgis.com/ (2018)"}}, {"type": "node", "id": 6402068396, "lat": 38.7459978, "lon": -90.5581616, "tags": {"addr:city": "Saint Peters", "addr:housenumber": "1220", "addr:postcode": "63303", "addr:street": "Triangle Drive", "source:addr": "https://gis.sccmo.opendata.arcgis.com/ (2018)"}}, {"type": "node", "id": 6402068397, "lat": 38.7453912, "lon": -90.5586176, "tags": {"addr:city": "Saint Peters", "addr:housenumber": "1335", "addr:postcode": "63303", "addr:street": "Triangle Drive", "source:addr": "https://gis.sccmo.opendata.arcgis.com/ (2018)"}}, {"type": "node", "id": 6402068398, "lat": 38.7461384, "lon": -90.5590366, "tags": {"addr:city": "Saint Peters", "addr:housenumber": "1200", "addr:postcode": "63303", "addr:street": "Triangle Drive", "source:addr": "https://gis.sccmo.opendata.arcgis.com/ (2018)"}}, {"type": "node", "id": 6402068399, "lat": 38.7450849, "lon": -90.559052, "tags": {"addr:city": "Saint Peters", "addr:housenumber": "1374", "addr:postcode": "63303", "addr:street": "Triangle Drive", "source:addr": "https://gis.sccmo.opendata.arcgis.com/ (2018)"}}, {"type": "node", "id": 6402068400, "lat": 38.7451593, "lon": -90.5589936, "tags": {"addr:city": "Saint Peters", "addr:housenumber": "1370", "addr:postcode": "63303", "addr:street": "Triangle Drive", "source:addr": "https://gis.sccmo.opendata.arcgis.com/ (2018)"}}, {"type": "node", "id": 6402068401, "lat": 38.7451022, "lon": -90.558895, "tags": {"addr:city": "Saint Peters", "addr:housenumber": "1368", "addr:postcode": "63303", "addr:street": "Triangle Drive", "source:addr": "https://gis.sccmo.opendata.arcgis.com/ (2018)"}}, {"type": "node", "id": 6402068402, "lat": 38.7450392, "lon": -90.5589497, "tags": {"addr:city": "Saint Peters", "addr:housenumber": "1372", "addr:postcode": "63303", "addr:street": "Triangle Drive", "source:addr": "https://gis.sccmo.opendata.arcgis.com/ (2018)"}}, {"type": "node", "id": 6402068403, "lat": 38.7450772, "lon": -90.5573939, "tags": {"addr:city": "Saint Peters", "addr:housenumber": "1292", "addr:postcode": "63303", "addr:street": "Triangle Drive", "source:addr": "https://gis.sccmo.opendata.arcgis.com/ (2018)"}}, {"type": "node", "id": 6402068404, "lat": 38.7449685, "lon": -90.5574011, "tags": {"addr:city": "Saint Peters", "addr:housenumber": "1294", "addr:postcode": "63303", "addr:street": "Triangle Drive", "source:addr": "https://gis.sccmo.opendata.arcgis.com/ (2018)"}}, {"type": "node", "id": 6402068405, "lat": 38.7447309, "lon": -90.5576858, "tags": {"addr:city": "Saint Peters", "addr:housenumber": "1314", "addr:postcode": "63303", "addr:street": "Triangle Drive", "source:addr": "https://gis.sccmo.opendata.arcgis.com/ (2018)"}}, {"type": "node", "id": 6402068406, "lat": 38.7449742, "lon": -90.557507, "tags": {"addr:city": "Saint Peters", "addr:housenumber": "1290", "addr:postcode": "63303", "addr:street": "Triangle Drive", "source:addr": "https://gis.sccmo.opendata.arcgis.com/ (2018)"}}, {"type": "node", "id": 6402068407, "lat": 38.7448825, "lon": -90.5576603, "tags": {"addr:city": "Saint Peters", "addr:housenumber": "1308", "addr:postcode": "63303", "addr:street": "Triangle Drive", "source:addr": "https://gis.sccmo.opendata.arcgis.com/ (2018)"}}, {"type": "node", "id": 6402068408, "lat": 38.7448225, "lon": -90.5575799, "tags": {"addr:city": "Saint Peters", "addr:housenumber": "1312", "addr:postcode": "63303", "addr:street": "Triangle Drive", "source:addr": "https://gis.sccmo.opendata.arcgis.com/ (2018)"}}, {"type": "node", "id": 6402068409, "lat": 38.7448679, "lon": -90.5583177, "tags": {"addr:city": "Saint Peters", "addr:housenumber": "1348", "addr:postcode": "63303", "addr:street": "Triangle Drive", "source:addr": "https://gis.sccmo.opendata.arcgis.com/ (2018)"}}, {"type": "node", "id": 6402068410, "lat": 38.7448878, "lon": -90.5585113, "tags": {"addr:city": "Saint Peters", "addr:housenumber": "1354", "addr:postcode": "63303", "addr:street": "Triangle Drive", "source:addr": "https://gis.sccmo.opendata.arcgis.com/ (2018)"}}, {"type": "node", "id": 6402068411, "lat": 38.744805, "lon": -90.5583834, "tags": {"addr:city": "Saint Peters", "addr:housenumber": "1352", "addr:postcode": "63303", "addr:street": "Triangle Drive", "source:addr": "https://gis.sccmo.opendata.arcgis.com/ (2018)"}}, {"type": "node", "id": 6402068412, "lat": 38.7449451, "lon": -90.5584639, "tags": {"addr:city": "Saint Peters", "addr:housenumber": "1350", "addr:postcode": "63303", "addr:street": "Triangle Drive", "source:addr": "https://gis.sccmo.opendata.arcgis.com/ (2018)"}}, {"type": "node", "id": 6402068413, "lat": 38.7455002, "lon": -90.5579822, "tags": {"addr:city": "Saint Peters", "addr:housenumber": "1252", "addr:postcode": "63303", "addr:street": "Triangle Drive", "source:addr": "https://gis.sccmo.opendata.arcgis.com/ (2018)"}}, {"type": "node", "id": 6402068414, "lat": 38.7447795, "lon": -90.5577844, "tags": {"addr:city": "Saint Peters", "addr:housenumber": "1310", "addr:postcode": "63303", "addr:street": "Triangle Drive", "source:addr": "https://gis.sccmo.opendata.arcgis.com/ (2018)"}}, {"type": "node", "id": 6402068415, "lat": 38.7454231, "lon": -90.5578324, "tags": {"addr:city": "Saint Peters", "addr:housenumber": "1254", "addr:postcode": "63303", "addr:street": "Triangle Drive", "source:addr": "https://gis.sccmo.opendata.arcgis.com/ (2018)"}}, {"type": "node", "id": 6402068416, "lat": 38.7453429, "lon": -90.557909, "tags": {"addr:city": "Saint Peters", "addr:housenumber": "1250", "addr:postcode": "63303", "addr:street": "Triangle Drive", "source:addr": "https://gis.sccmo.opendata.arcgis.com/ (2018)"}}, {"type": "node", "id": 6402068417, "lat": 38.7452572, "lon": -90.5577702, "tags": {"addr:city": "Saint Peters", "addr:housenumber": "1268", "addr:postcode": "63303", "addr:street": "Triangle Drive", "source:addr": "https://gis.sccmo.opendata.arcgis.com/ (2018)"}}, {"type": "node", "id": 6402068514, "lat": 38.7464107, "lon": -90.5601195, "tags": {"addr:city": "Saint Peters", "addr:housenumber": "2970", "addr:postcode": "63303", "addr:street": "Imperial Drive", "source:addr": "https://gis.sccmo.opendata.arcgis.com/ (2018)"}}, {"type": "node", "id": 6402068515, "lat": 38.7460232, "lon": -90.5620602, "tags": {"addr:city": "Saint Peters", "addr:housenumber": "2995", "addr:postcode": "63303", "addr:street": "Imperial Drive", "source:addr": "https://gis.sccmo.opendata.arcgis.com/ (2018)"}}, {"type": "node", "id": 6402068516, "lat": 38.7466918, "lon": -90.5597181, "tags": {"addr:city": "Saint Peters", "addr:housenumber": "2962", "addr:postcode": "63303", "addr:street": "Imperial Drive", "source:addr": "https://gis.sccmo.opendata.arcgis.com/ (2018)"}}, {"type": "node", "id": 6402068517, "lat": 38.7459624, "lon": -90.5623149, "tags": {"addr:city": "Saint Peters", "addr:housenumber": "2999", "addr:postcode": "63303", "addr:street": "Imperial Drive", "source:addr": "https://gis.sccmo.opendata.arcgis.com/ (2018)"}}, {"type": "node", "id": 6402068519, "lat": 38.7467712, "lon": -90.5594889, "tags": {"addr:city": "Saint Peters", "addr:housenumber": "2958", "addr:postcode": "63303", "addr:street": "Imperial Drive", "source:addr": "https://gis.sccmo.opendata.arcgis.com/ (2018)"}}, {"type": "node", "id": 6402068520, "lat": 38.7460795, "lon": -90.5599323, "tags": {"addr:city": "Saint Peters", "addr:housenumber": "2969", "addr:postcode": "63303", "addr:street": "Imperial Drive", "source:addr": "https://gis.sccmo.opendata.arcgis.com/ (2018)"}}, {"type": "node", "id": 6402068525, "lat": 38.7463482, "lon": -90.56039, "tags": {"addr:city": "Saint Peters", "addr:housenumber": "2974", "addr:postcode": "63303", "addr:street": "Imperial Drive", "source:addr": "https://gis.sccmo.opendata.arcgis.com/ (2018)"}}, {"type": "node", "id": 6402068526, "lat": 38.7464015, "lon": -90.558209, "tags": {"addr:city": "Saint Peters", "addr:housenumber": "2945", "addr:postcode": "63303", "addr:street": "Imperial Drive", "source:addr": "https://gis.sccmo.opendata.arcgis.com/ (2018)"}}, {"type": "node", "id": 6402068528, "lat": 38.7463988, "lon": -90.5593943, "tags": {"addr:city": "Saint Peters", "addr:housenumber": "2961", "addr:postcode": "63303", "addr:street": "Imperial Drive", "source:addr": "https://gis.sccmo.opendata.arcgis.com/ (2018)"}}, {"type": "node", "id": 6402068529, "lat": 38.7468846, "lon": -90.5592751, "tags": {"addr:city": "Saint Peters", "addr:housenumber": "2954", "addr:postcode": "63303", "addr:street": "Imperial Drive", "source:addr": "https://gis.sccmo.opendata.arcgis.com/ (2018)"}}, {"type": "node", "id": 6402068530, "lat": 38.7463116, "lon": -90.5616078, "tags": {"addr:city": "Saint Peters", "addr:housenumber": "2990", "addr:postcode": "63303", "addr:street": "Imperial Drive", "source:addr": "https://gis.sccmo.opendata.arcgis.com/ (2018)"}}, {"type": "node", "id": 6402068531, "lat": 38.7465818, "lon": -90.5598752, "tags": {"addr:city": "Saint Peters", "addr:housenumber": "2966", "addr:postcode": "63303", "addr:street": "Imperial Drive", "source:addr": "https://gis.sccmo.opendata.arcgis.com/ (2018)"}}, {"type": "node", "id": 6402068532, "lat": 38.7460142, "lon": -90.5601699, "tags": {"addr:city": "Saint Peters", "addr:housenumber": "2973", "addr:postcode": "63303", "addr:street": "Imperial Drive", "source:addr": "https://gis.sccmo.opendata.arcgis.com/ (2018)"}}, {"type": "node", "id": 6402068533, "lat": 38.7463473, "lon": -90.5608476, "tags": {"addr:city": "Saint Peters", "addr:housenumber": "2982", "addr:postcode": "63303", "addr:street": "Imperial Drive", "source:addr": "https://gis.sccmo.opendata.arcgis.com/ (2018)"}}, {"type": "node", "id": 6402068534, "lat": 38.7459694, "lon": -90.5604249, "tags": {"addr:city": "Saint Peters", "addr:housenumber": "2977", "addr:postcode": "63303", "addr:street": "Imperial Drive", "source:addr": "https://gis.sccmo.opendata.arcgis.com/ (2018)"}}, {"type": "node", "id": 6402068535, "lat": 38.7459819, "lon": -90.5610955, "tags": {"addr:city": "Saint Peters", "addr:housenumber": "2987", "addr:postcode": "63303", "addr:street": "Imperial Drive", "source:addr": "https://gis.sccmo.opendata.arcgis.com/ (2018)"}}, {"type": "node", "id": 6402068537, "lat": 38.7463102, "lon": -90.5606197, "tags": {"addr:city": "Saint Peters", "addr:housenumber": "2978", "addr:postcode": "63303", "addr:street": "Imperial Drive", "source:addr": "https://gis.sccmo.opendata.arcgis.com/ (2018)"}}, {"type": "node", "id": 6402068539, "lat": 38.7462019, "lon": -90.5626279, "tags": {"addr:city": "Saint Peters", "addr:housenumber": "2998", "addr:postcode": "63303", "addr:street": "Imperial Drive", "source:addr": "https://gis.sccmo.opendata.arcgis.com/ (2018)"}}, {"type": "node", "id": 6402068547, "lat": 38.7465094, "lon": -90.55892, "tags": {"addr:city": "Saint Peters", "addr:housenumber": "2953", "addr:postcode": "63303", "addr:street": "Imperial Drive", "source:addr": "https://gis.sccmo.opendata.arcgis.com/ (2018)"}}, {"type": "node", "id": 6402068548, "lat": 38.7465, "lon": -90.5586508, "tags": {"addr:city": "Saint Peters", "addr:housenumber": "2951", "addr:postcode": "63303", "addr:street": "Imperial Drive", "source:addr": "https://gis.sccmo.opendata.arcgis.com/ (2018)"}}, {"type": "node", "id": 6402068549, "lat": 38.7464757, "lon": -90.5584326, "tags": {"addr:city": "Saint Peters", "addr:housenumber": "2947", "addr:postcode": "63303", "addr:street": "Imperial Drive", "source:addr": "https://gis.sccmo.opendata.arcgis.com/ (2018)"}}, {"type": "node", "id": 6402068551, "lat": 38.7464735, "lon": -90.5591424, "tags": {"addr:city": "Saint Peters", "addr:housenumber": "2957", "addr:postcode": "63303", "addr:street": "Imperial Drive", "source:addr": "https://gis.sccmo.opendata.arcgis.com/ (2018)"}}, {"type": "node", "id": 6402068552, "lat": 38.7463813, "lon": -90.5579815, "tags": {"addr:city": "Saint Peters", "addr:housenumber": "2943", "addr:postcode": "63303", "addr:street": "Imperial Drive", "source:addr": "https://gis.sccmo.opendata.arcgis.com/ (2018)"}}, {"type": "node", "id": 6402068553, "lat": 38.7459985, "lon": -90.5618142, "tags": {"addr:city": "Saint Peters", "addr:housenumber": "2993", "addr:postcode": "63303", "addr:street": "Imperial Drive", "source:addr": "https://gis.sccmo.opendata.arcgis.com/ (2018)"}}, {"type": "node", "id": 6402068554, "lat": 38.7459774, "lon": -90.5608672, "tags": {"addr:city": "Saint Peters", "addr:housenumber": "2985", "addr:postcode": "63303", "addr:street": "Imperial Drive", "source:addr": "https://gis.sccmo.opendata.arcgis.com/ (2018)"}}, {"type": "node", "id": 6402068556, "lat": 38.7459861, "lon": -90.5606349, "tags": {"addr:city": "Saint Peters", "addr:housenumber": "2981", "addr:postcode": "63303", "addr:street": "Imperial Drive", "source:addr": "https://gis.sccmo.opendata.arcgis.com/ (2018)"}}, {"type": "node", "id": 6402068558, "lat": 38.7460057, "lon": -90.5613125, "tags": {"addr:city": "Saint Peters", "addr:housenumber": "2989", "addr:postcode": "63303", "addr:street": "Imperial Drive", "source:addr": "https://gis.sccmo.opendata.arcgis.com/ (2018)"}}, {"type": "node", "id": 6402068559, "lat": 38.7459799, "lon": -90.5615872, "tags": {"addr:city": "Saint Peters", "addr:housenumber": "2991", "addr:postcode": "63303", "addr:street": "Imperial Drive", "source:addr": "https://gis.sccmo.opendata.arcgis.com/ (2018)"}}, {"type": "node", "id": 6481762141, "lat": 38.7463855, "lon": -90.5613041, "tags": {"addr:city": "Saint Peters", "addr:housenumber": "31", "addr:postcode": "63303", "addr:street": "Old Winery Court", "source:addr": "https://gis.sccmo.opendata.arcgis.com/ (2018)"}}, {"type": "node", "id": 6481762145, "lat": 38.7469577, "lon": -90.5623061, "tags": {"addr:city": "Saint Peters", "addr:housenumber": "27", "addr:postcode": "63303", "addr:street": "Imperial Circle", "source:addr": "https://gis.sccmo.opendata.arcgis.com/ (2018)"}}, {"type": "node", "id": 6481762146, "lat": 38.7466174, "lon": -90.5619361, "tags": {"addr:city": "Saint Peters", "addr:housenumber": "22", "addr:postcode": "63303", "addr:street": "Imperial Circle", "source:addr": "https://gis.sccmo.opendata.arcgis.com/ (2018)"}}, {"type": "node", "id": 6481762150, "lat": 38.7466, "lon": -90.5624774, "tags": {"addr:city": "Saint Peters", "addr:housenumber": "23", "addr:postcode": "63303", "addr:street": "Imperial Circle", "source:addr": "https://gis.sccmo.opendata.arcgis.com/ (2018)"}}, {"type": "node", "id": 6481762151, "lat": 38.7464021, "lon": -90.5619301, "tags": {"addr:city": "Saint Peters", "addr:housenumber": "20", "addr:postcode": "63303", "addr:street": "Imperial Circle", "source:addr": "https://gis.sccmo.opendata.arcgis.com/ (2018)"}}, {"type": "node", "id": 6481762153, "lat": 38.7469401, "lon": -90.561162, "tags": {"addr:city": "Saint Peters", "addr:housenumber": "37", "addr:postcode": "63303", "addr:street": "Old Winery Court", "source:addr": "https://gis.sccmo.opendata.arcgis.com/ (2018)"}}, {"type": "node", "id": 6481762155, "lat": 38.7468081, "lon": -90.5607485, "tags": {"addr:city": "Saint Peters", "addr:housenumber": "34", "addr:postcode": "63303", "addr:street": "Old Winery Court", "source:addr": "https://gis.sccmo.opendata.arcgis.com/ (2018)"}}, {"type": "node", "id": 6481762164, "lat": 38.7466399, "lon": -90.5608407, "tags": {"addr:city": "Saint Peters", "addr:housenumber": "32", "addr:postcode": "63303", "addr:street": "Old Winery Court", "source:addr": "https://gis.sccmo.opendata.arcgis.com/ (2018)"}}, {"type": "node", "id": 6481762168, "lat": 38.7469415, "lon": -90.5609109, "tags": {"addr:city": "Saint Peters", "addr:housenumber": "36", "addr:postcode": "63303", "addr:street": "Old Winery Court", "source:addr": "https://gis.sccmo.opendata.arcgis.com/ (2018)"}}, {"type": "node", "id": 6481762170, "lat": 38.7467633, "lon": -90.5612875, "tags": {"addr:city": "Saint Peters", "addr:housenumber": "35", "addr:postcode": "63303", "addr:street": "Old Winery Court", "source:addr": "https://gis.sccmo.opendata.arcgis.com/ (2018)"}}, {"type": "node", "id": 6481762173, "lat": 38.7469306, "lon": -90.5620992, "tags": {"addr:city": "Saint Peters", "addr:housenumber": "26", "addr:postcode": "63303", "addr:street": "Imperial Circle", "source:addr": "https://gis.sccmo.opendata.arcgis.com/ (2018)"}}, {"type": "node", "id": 6481762177, "lat": 38.7467934, "lon": -90.5624757, "tags": {"addr:city": "Saint Peters", "addr:housenumber": "25", "addr:postcode": "63303", "addr:street": "Imperial Circle", "source:addr": "https://gis.sccmo.opendata.arcgis.com/ (2018)"}}, {"type": "node", "id": 6481762178, "lat": 38.7463627, "lon": -90.562352, "tags": {"addr:city": "Saint Peters", "addr:housenumber": "21", "addr:postcode": "63303", "addr:street": "Imperial Circle", "source:addr": "https://gis.sccmo.opendata.arcgis.com/ (2018)"}}, {"type": "node", "id": 6481762179, "lat": 38.7466015, "lon": -90.5612643, "tags": {"addr:city": "Saint Peters", "addr:housenumber": "33", "addr:postcode": "63303", "addr:street": "Old Winery Court", "source:addr": "https://gis.sccmo.opendata.arcgis.com/ (2018)"}}, {"type": "node", "id": 6481762294, "lat": 38.7468123, "lon": -90.5619278, "tags": {"addr:city": "Saint Peters", "addr:housenumber": "24", "addr:postcode": "63303", "addr:street": "Imperial Circle", "source:addr": "https://gis.sccmo.opendata.arcgis.com/ (2018)"}}, {"type": "node", "id": 6481762338, "lat": 38.7490966, "lon": -90.5585095, "tags": {"addr:city": "Saint Peters", "addr:housenumber": "1448", "addr:postcode": "63303", "addr:street": "Plantation Manor Circle", "source:addr": "https://gis.sccmo.opendata.arcgis.com/ (2018)"}}, {"type": "node", "id": 6481762339, "lat": 38.7486505, "lon": -90.5582461, "tags": {"addr:city": "Saint Peters", "addr:housenumber": "1438", "addr:postcode": "63303", "addr:street": "Plantation Manor Circle", "source:addr": "https://gis.sccmo.opendata.arcgis.com/ (2018)"}}, {"type": "node", "id": 6481762340, "lat": 38.7489117, "lon": -90.5579392, "tags": {"addr:city": "Saint Peters", "addr:housenumber": "1442", "addr:postcode": "63303", "addr:street": "Plantation Manor Circle", "source:addr": "https://gis.sccmo.opendata.arcgis.com/ (2018)"}}, {"type": "node", "id": 6481762341, "lat": 38.7489638, "lon": -90.5586665, "tags": {"addr:city": "Saint Peters", "addr:housenumber": "1450", "addr:postcode": "63303", "addr:street": "Plantation Manor Circle", "source:addr": "https://gis.sccmo.opendata.arcgis.com/ (2018)"}}, {"type": "node", "id": 6481762342, "lat": 38.7491206, "lon": -90.5580382, "tags": {"addr:city": "Saint Peters", "addr:housenumber": "1444", "addr:postcode": "63303", "addr:street": "Plantation Manor Circle", "source:addr": "https://gis.sccmo.opendata.arcgis.com/ (2018)"}}, {"type": "node", "id": 6481762343, "lat": 38.7487481, "lon": -90.5580239, "tags": {"addr:city": "Saint Peters", "addr:housenumber": "1440", "addr:postcode": "63303", "addr:street": "Plantation Manor Circle", "source:addr": "https://gis.sccmo.opendata.arcgis.com/ (2018)"}}, {"type": "node", "id": 6481762344, "lat": 38.7484442, "lon": -90.558655, "tags": {"addr:city": "Saint Peters", "addr:housenumber": "1445", "addr:postcode": "63303", "addr:street": "Plantation Manor Court", "source:addr": "https://gis.sccmo.opendata.arcgis.com/ (2018)"}}, {"type": "node", "id": 6481762345, "lat": 38.7467586, "lon": -90.5578334, "tags": {"addr:city": "Saint Peters", "addr:housenumber": "1400", "addr:postcode": "63303", "addr:street": "Plantation Manor Court", "source:addr": "https://gis.sccmo.opendata.arcgis.com/ (2018)"}}, {"type": "node", "id": 6481762346, "lat": 38.7469263, "lon": -90.5577994, "tags": {"addr:city": "Saint Peters", "addr:housenumber": "1404", "addr:postcode": "63303", "addr:street": "Plantation Manor Court", "source:addr": "https://gis.sccmo.opendata.arcgis.com/ (2018)"}}, {"type": "node", "id": 6481762347, "lat": 38.7483962, "lon": -90.5580268, "tags": {"addr:city": "Saint Peters", "addr:housenumber": "1436", "addr:postcode": "63303", "addr:street": "Plantation Manor Court", "source:addr": "https://gis.sccmo.opendata.arcgis.com/ (2018)"}}, {"type": "node", "id": 6481762348, "lat": 38.7470219, "lon": -90.5582354, "tags": {"addr:city": "Saint Peters", "addr:housenumber": "1405", "addr:postcode": "63303", "addr:street": "Plantation Manor Court", "source:addr": "https://gis.sccmo.opendata.arcgis.com/ (2018)"}}, {"type": "node", "id": 6481762349, "lat": 38.7474092, "lon": -90.5582111, "tags": {"addr:city": "Saint Peters", "addr:housenumber": "1413", "addr:postcode": "63303", "addr:street": "Plantation Manor Court", "source:addr": "https://gis.sccmo.opendata.arcgis.com/ (2018)"}}, {"type": "node", "id": 6481762350, "lat": 38.7471156, "lon": -90.5577573, "tags": {"addr:city": "Saint Peters", "addr:housenumber": "1408", "addr:postcode": "63303", "addr:street": "Plantation Manor Court", "source:addr": "https://gis.sccmo.opendata.arcgis.com/ (2018)"}}, {"type": "node", "id": 6481762351, "lat": 38.7489909, "lon": -90.5598986, "tags": {"addr:city": "Saint Peters", "addr:housenumber": "1470", "addr:postcode": "63303", "addr:street": "Plantation Manor Court", "source:addr": "https://gis.sccmo.opendata.arcgis.com/ (2018)"}}, {"type": "node", "id": 6481762352, "lat": 38.7478185, "lon": -90.5578369, "tags": {"addr:city": "Saint Peters", "addr:housenumber": "1424", "addr:postcode": "63303", "addr:street": "Plantation Manor Court", "source:addr": "https://gis.sccmo.opendata.arcgis.com/ (2018)"}}, {"type": "node", "id": 6481762353, "lat": 38.7479439, "lon": -90.55834, "tags": {"addr:city": "Saint Peters", "addr:housenumber": "1429", "addr:postcode": "63303", "addr:street": "Plantation Manor Court", "source:addr": "https://gis.sccmo.opendata.arcgis.com/ (2018)"}}, {"type": "node", "id": 6481762354, "lat": 38.7491434, "lon": -90.5596971, "tags": {"addr:city": "Saint Peters", "addr:housenumber": "1466", "addr:postcode": "63303", "addr:street": "Plantation Manor Court", "source:addr": "https://gis.sccmo.opendata.arcgis.com/ (2018)"}}, {"type": "node", "id": 6481762355, "lat": 38.7491069, "lon": -90.5591691, "tags": {"addr:city": "Saint Peters", "addr:housenumber": "1458", "addr:postcode": "63303", "addr:street": "Plantation Manor Court", "source:addr": "https://gis.sccmo.opendata.arcgis.com/ (2018)"}}, {"type": "node", "id": 6481762356, "lat": 38.7485801, "lon": -90.5588356, "tags": {"addr:city": "Saint Peters", "addr:housenumber": "1453", "addr:postcode": "63303", "addr:street": "Plantation Manor Court", "source:addr": "https://gis.sccmo.opendata.arcgis.com/ (2018)"}}, {"type": "node", "id": 6481762357, "lat": 38.747226, "lon": -90.5581935, "tags": {"addr:city": "Saint Peters", "addr:housenumber": "1409", "addr:postcode": "63303", "addr:street": "Plantation Manor Court", "source:addr": "https://gis.sccmo.opendata.arcgis.com/ (2018)"}}, {"type": "node", "id": 6481762358, "lat": 38.7491136, "lon": -90.5594003, "tags": {"addr:city": "Saint Peters", "addr:housenumber": "1462", "addr:postcode": "63303", "addr:street": "Plantation Manor Court", "source:addr": "https://gis.sccmo.opendata.arcgis.com/ (2018)"}}, {"type": "node", "id": 6481762359, "lat": 38.7492281, "lon": -90.5582761, "tags": {"addr:city": "Saint Peters", "addr:housenumber": "1446", "addr:postcode": "63303", "addr:street": "Plantation Manor Circle", "source:addr": "https://gis.sccmo.opendata.arcgis.com/ (2018)"}}, {"type": "node", "id": 6481762360, "lat": 38.7490293, "lon": -90.5589655, "tags": {"addr:city": "Saint Peters", "addr:housenumber": "1454", "addr:postcode": "63303", "addr:street": "Plantation Manor Court", "source:addr": "https://gis.sccmo.opendata.arcgis.com/ (2018)"}}, {"type": "node", "id": 6481762361, "lat": 38.7486698, "lon": -90.5593665, "tags": {"addr:city": "Saint Peters", "addr:housenumber": "1461", "addr:postcode": "63303", "addr:street": "Plantation Manor Court", "source:addr": "https://gis.sccmo.opendata.arcgis.com/ (2018)"}}, {"type": "node", "id": 6481762362, "lat": 38.7474696, "lon": -90.5577852, "tags": {"addr:city": "Saint Peters", "addr:housenumber": "1416", "addr:postcode": "63303", "addr:street": "Plantation Manor Court", "source:addr": "https://gis.sccmo.opendata.arcgis.com/ (2018)"}}, {"type": "node", "id": 6481762363, "lat": 38.7482211, "lon": -90.557966, "tags": {"addr:city": "Saint Peters", "addr:housenumber": "1432", "addr:postcode": "63303", "addr:street": "Plantation Manor Court", "source:addr": "https://gis.sccmo.opendata.arcgis.com/ (2018)"}}, {"type": "node", "id": 6481762364, "lat": 38.7472999, "lon": -90.5577224, "tags": {"addr:city": "Saint Peters", "addr:housenumber": "1412", "addr:postcode": "63303", "addr:street": "Plantation Manor Court", "source:addr": "https://gis.sccmo.opendata.arcgis.com/ (2018)"}}, {"type": "node", "id": 6481762365, "lat": 38.7476597, "lon": -90.5577802, "tags": {"addr:city": "Saint Peters", "addr:housenumber": "1420", "addr:postcode": "63303", "addr:street": "Plantation Manor Court", "source:addr": "https://gis.sccmo.opendata.arcgis.com/ (2018)"}}, {"type": "node", "id": 6481762366, "lat": 38.7475745, "lon": -90.558242, "tags": {"addr:city": "Saint Peters", "addr:housenumber": "1417", "addr:postcode": "63303", "addr:street": "Plantation Manor Court", "source:addr": "https://gis.sccmo.opendata.arcgis.com/ (2018)"}}, {"type": "node", "id": 6481762367, "lat": 38.7480138, "lon": -90.5578653, "tags": {"addr:city": "Saint Peters", "addr:housenumber": "1428", "addr:postcode": "63303", "addr:street": "Plantation Manor Court", "source:addr": "https://gis.sccmo.opendata.arcgis.com/ (2018)"}}, {"type": "node", "id": 6481762368, "lat": 38.7477451, "lon": -90.5583105, "tags": {"addr:city": "Saint Peters", "addr:housenumber": "1421", "addr:postcode": "63303", "addr:street": "Plantation Manor Court", "source:addr": "https://gis.sccmo.opendata.arcgis.com/ (2018)"}}, {"type": "node", "id": 6481762369, "lat": 38.7481075, "lon": -90.5584547, "tags": {"addr:city": "Saint Peters", "addr:housenumber": "1433", "addr:postcode": "63303", "addr:street": "Plantation Manor Court", "source:addr": "https://gis.sccmo.opendata.arcgis.com/ (2018)"}}, {"type": "node", "id": 6481762370, "lat": 38.7482837, "lon": -90.5585448, "tags": {"addr:city": "Saint Peters", "addr:housenumber": "1437", "addr:postcode": "63303", "addr:street": "Plantation Manor Court", "source:addr": "https://gis.sccmo.opendata.arcgis.com/ (2018)"}}, {"type": "node", "id": 6481762371, "lat": 38.7486752, "lon": -90.5596068, "tags": {"addr:city": "Saint Peters", "addr:housenumber": "1465", "addr:postcode": "63303", "addr:street": "Plantation Manor Court", "source:addr": "https://gis.sccmo.opendata.arcgis.com/ (2018)"}}, {"type": "node", "id": 6481762372, "lat": 38.7487721, "lon": -90.5598516, "tags": {"addr:city": "Saint Peters", "addr:housenumber": "1469", "addr:postcode": "63303", "addr:street": "Plantation Manor Court", "source:addr": "https://gis.sccmo.opendata.arcgis.com/ (2018)"}}, {"type": "node", "id": 6481762373, "lat": 38.746847, "lon": -90.5583176, "tags": {"addr:city": "Saint Peters", "addr:housenumber": "1401", "addr:postcode": "63303", "addr:street": "Plantation Manor Court", "source:addr": "https://gis.sccmo.opendata.arcgis.com/ (2018)"}}, {"type": "node", "id": 6481762374, "lat": 38.7486636, "lon": -90.5590569, "tags": {"addr:city": "Saint Peters", "addr:housenumber": "1457", "addr:postcode": "63303", "addr:street": "Plantation Manor Court", "source:addr": "https://gis.sccmo.opendata.arcgis.com/ (2018)"}}, {"type": "node", "id": 6481762375, "lat": 38.7470558, "lon": -90.5568492, "tags": {"addr:city": "Saint Peters", "addr:housenumber": "1519", "addr:postcode": "63303", "addr:street": "Heritage Manor Court", "source:addr": "https://gis.sccmo.opendata.arcgis.com/ (2018)"}}, {"type": "node", "id": 6481762380, "lat": 38.7452746, "lon": -90.5567502, "tags": {"addr:city": "Saint Peters", "addr:housenumber": "1503", "addr:postcode": "63303", "addr:street": "Heritage Manor Court", "source:addr": "https://gis.sccmo.opendata.arcgis.com/ (2018)"}}, {"type": "node", "id": 6481762384, "lat": 38.7474786, "lon": -90.5568509, "tags": {"addr:city": "Saint Peters", "addr:housenumber": "1523", "addr:postcode": "63303", "addr:street": "Heritage Manor Court", "source:addr": "https://gis.sccmo.opendata.arcgis.com/ (2018)"}}, {"type": "node", "id": 6481762385, "lat": 38.7455004, "lon": -90.5568677, "tags": {"addr:city": "Saint Peters", "addr:housenumber": "1505", "addr:postcode": "63303", "addr:street": "Heritage Manor Court", "source:addr": "https://gis.sccmo.opendata.arcgis.com/ (2018)"}}, {"type": "node", "id": 6481762387, "lat": 38.7456483, "lon": -90.5571405, "tags": {"addr:city": "Saint Peters", "addr:housenumber": "1507", "addr:postcode": "63303", "addr:street": "Heritage Manor Court", "source:addr": "https://gis.sccmo.opendata.arcgis.com/ (2018)"}}, {"type": "node", "id": 6481762388, "lat": 38.7487204, "lon": -90.5568051, "tags": {"addr:city": "Saint Peters", "addr:housenumber": "1537", "addr:postcode": "63303", "addr:street": "Heritage Manor Court", "source:addr": "https://gis.sccmo.opendata.arcgis.com/ (2018)"}}, {"type": "node", "id": 6481762389, "lat": 38.747754, "lon": -90.5568226, "tags": {"addr:city": "Saint Peters", "addr:housenumber": "1525", "addr:postcode": "63303", "addr:street": "Heritage Manor Court", "source:addr": "https://gis.sccmo.opendata.arcgis.com/ (2018)"}}, {"type": "node", "id": 6481762390, "lat": 38.7485256, "lon": -90.5567725, "tags": {"addr:city": "Saint Peters", "addr:housenumber": "1535", "addr:postcode": "63303", "addr:street": "Heritage Manor Court", "source:addr": "https://gis.sccmo.opendata.arcgis.com/ (2018)"}}, {"type": "node", "id": 6481762391, "lat": 38.7472589, "lon": -90.5568418, "tags": {"addr:city": "Saint Peters", "addr:housenumber": "1521", "addr:postcode": "63303", "addr:street": "Heritage Manor Court", "source:addr": "https://gis.sccmo.opendata.arcgis.com/ (2018)"}}, {"type": "node", "id": 6481762392, "lat": 38.7489868, "lon": -90.5569093, "tags": {"addr:city": "Saint Peters", "addr:housenumber": "1539", "addr:postcode": "63303", "addr:street": "Heritage Manor Court", "source:addr": "https://gis.sccmo.opendata.arcgis.com/ (2018)"}}, {"type": "node", "id": 6481762395, "lat": 38.7465416, "lon": -90.556926, "tags": {"addr:city": "Saint Peters", "addr:housenumber": "1515", "addr:postcode": "63303", "addr:street": "Heritage Manor Court", "source:addr": "https://gis.sccmo.opendata.arcgis.com/ (2018)"}}, {"type": "node", "id": 6481762396, "lat": 38.7463285, "lon": -90.5570119, "tags": {"addr:city": "Saint Peters", "addr:housenumber": "1513", "addr:postcode": "63303", "addr:street": "Heritage Manor Court", "source:addr": "https://gis.sccmo.opendata.arcgis.com/ (2018)"}}, {"type": "node", "id": 6481762397, "lat": 38.746103, "lon": -90.5571049, "tags": {"addr:city": "Saint Peters", "addr:housenumber": "1511", "addr:postcode": "63303", "addr:street": "Heritage Manor Court", "source:addr": "https://gis.sccmo.opendata.arcgis.com/ (2018)"}}, {"type": "node", "id": 6481762400, "lat": 38.7480691, "lon": -90.5568117, "tags": {"addr:city": "Saint Peters", "addr:housenumber": "1527", "addr:postcode": "63303", "addr:street": "Heritage Manor Court", "source:addr": "https://gis.sccmo.opendata.arcgis.com/ (2018)"}}, {"type": "node", "id": 6481762401, "lat": 38.7458794, "lon": -90.5573, "tags": {"addr:city": "Saint Peters", "addr:housenumber": "1509", "addr:postcode": "63303", "addr:street": "Heritage Manor Court", "source:addr": "https://gis.sccmo.opendata.arcgis.com/ (2018)"}}, {"type": "node", "id": 6481762404, "lat": 38.7468158, "lon": -90.5568664, "tags": {"addr:city": "Saint Peters", "addr:housenumber": "1517", "addr:postcode": "63303", "addr:street": "Heritage Manor Court", "source:addr": "https://gis.sccmo.opendata.arcgis.com/ (2018)"}}, {"type": "node", "id": 6557369232, "lat": 38.7475177, "lon": -90.5592162, "tags": {"addr:city": "Saint Peters", "addr:housenumber": "1319", "addr:postcode": "63303", "addr:street": "Magnolia Manor Court", "source:addr": "https://gis.sccmo.opendata.arcgis.com/ (2018)"}}, {"type": "node", "id": 6557369235, "lat": 38.7478691, "lon": -90.5597504, "tags": {"addr:city": "Saint Peters", "addr:housenumber": "1331", "addr:postcode": "63303", "addr:street": "Magnolia Manor Court", "source:addr": "https://gis.sccmo.opendata.arcgis.com/ (2018)"}}, {"type": "node", "id": 6557369266, "lat": 38.7478953, "lon": -90.5600346, "tags": {"addr:city": "Saint Peters", "addr:housenumber": "1339", "addr:postcode": "63303", "addr:street": "Magnolia Manor Court", "source:addr": "https://gis.sccmo.opendata.arcgis.com/ (2018)"}}, {"type": "node", "id": 6557369269, "lat": 38.7480761, "lon": -90.560208, "tags": {"addr:city": "Saint Peters", "addr:housenumber": "1343", "addr:postcode": "63303", "addr:street": "Magnolia Manor Court", "source:addr": "https://gis.sccmo.opendata.arcgis.com/ (2018)"}}, {"type": "node", "id": 6557369273, "lat": 38.7482847, "lon": -90.5601341, "tags": {"addr:city": "Saint Peters", "addr:housenumber": "1344", "addr:postcode": "63303", "addr:street": "Magnolia Manor Court", "source:addr": "https://gis.sccmo.opendata.arcgis.com/ (2018)"}}, {"type": "node", "id": 6557369282, "lat": 38.7478371, "lon": -90.5593766, "tags": {"addr:city": "Saint Peters", "addr:housenumber": "1323", "addr:postcode": "63303", "addr:street": "Magnolia Manor Court", "source:addr": "https://gis.sccmo.opendata.arcgis.com/ (2018)"}}, {"type": "node", "id": 6557369336, "lat": 38.7483646, "lon": -90.5598476, "tags": {"addr:city": "Saint Peters", "addr:housenumber": "1340", "addr:postcode": "63303", "addr:street": "Magnolia Manor Court", "source:addr": "https://gis.sccmo.opendata.arcgis.com/ (2018)"}}, {"type": "node", "id": 6557369349, "lat": 38.7481854, "lon": -90.559125, "tags": {"addr:city": "Saint Peters", "addr:housenumber": "1328", "addr:postcode": "63303", "addr:street": "Magnolia Manor Court", "source:addr": "https://gis.sccmo.opendata.arcgis.com/ (2018)"}}, {"type": "node", "id": 6557369351, "lat": 38.7474862, "lon": -90.5595125, "tags": {"addr:city": "Saint Peters", "addr:housenumber": "1317", "addr:postcode": "63303", "addr:street": "Magnolia Manor Circle", "source:addr": "https://gis.sccmo.opendata.arcgis.com/ (2018)"}}, {"type": "node", "id": 6557369353, "lat": 38.7483138, "lon": -90.5595947, "tags": {"addr:city": "Saint Peters", "addr:housenumber": "1336", "addr:postcode": "63303", "addr:street": "Magnolia Manor Court", "source:addr": "https://gis.sccmo.opendata.arcgis.com/ (2018)"}}, {"type": "node", "id": 6557369354, "lat": 38.7470771, "lon": -90.5591745, "tags": {"addr:city": "Saint Peters", "addr:housenumber": "1303", "addr:postcode": "63303", "addr:street": "Magnolia Manor Court", "source:addr": "https://gis.sccmo.opendata.arcgis.com/ (2018)"}}, {"type": "node", "id": 6557369356, "lat": 38.7482777, "lon": -90.5593346, "tags": {"addr:city": "Saint Peters", "addr:housenumber": "1332", "addr:postcode": "63303", "addr:street": "Magnolia Manor Court", "source:addr": "https://gis.sccmo.opendata.arcgis.com/ (2018)"}}, {"type": "node", "id": 6557369357, "lat": 38.7471367, "lon": -90.5595499, "tags": {"addr:city": "Saint Peters", "addr:housenumber": "1305", "addr:postcode": "63303", "addr:street": "Magnolia Manor Circle", "source:addr": "https://gis.sccmo.opendata.arcgis.com/ (2018)"}}, {"type": "node", "id": 6557369359, "lat": 38.7480154, "lon": -90.5589609, "tags": {"addr:city": "Saint Peters", "addr:housenumber": "1324", "addr:postcode": "63303", "addr:street": "Magnolia Manor Court", "source:addr": "https://gis.sccmo.opendata.arcgis.com/ (2018)"}}, {"type": "node", "id": 6557369367, "lat": 38.7471169, "lon": -90.5587552, "tags": {"addr:city": "Saint Peters", "addr:housenumber": "1304", "addr:postcode": "63303", "addr:street": "Magnolia Manor Court", "source:addr": "https://gis.sccmo.opendata.arcgis.com/ (2018)"}}, {"type": "node", "id": 6557369368, "lat": 38.7473118, "lon": -90.558785, "tags": {"addr:city": "Saint Peters", "addr:housenumber": "1308", "addr:postcode": "63303", "addr:street": "Magnolia Manor Court", "source:addr": "https://gis.sccmo.opendata.arcgis.com/ (2018)"}}, {"type": "node", "id": 6557369371, "lat": 38.7469235, "lon": -90.5587072, "tags": {"addr:city": "Saint Peters", "addr:housenumber": "1300", "addr:postcode": "63303", "addr:street": "Magnolia Manor Court", "source:addr": "https://gis.sccmo.opendata.arcgis.com/ (2018)"}}, {"type": "node", "id": 6557369373, "lat": 38.7474733, "lon": -90.5587637, "tags": {"addr:city": "Saint Peters", "addr:housenumber": "1312", "addr:postcode": "63303", "addr:street": "Magnolia Manor Court", "source:addr": "https://gis.sccmo.opendata.arcgis.com/ (2018)"}}, {"type": "node", "id": 6557369376, "lat": 38.7473137, "lon": -90.560185, "tags": {"addr:city": "Saint Peters", "addr:housenumber": "1311", "addr:postcode": "63303", "addr:street": "Magnolia Manor Circle", "source:addr": "https://gis.sccmo.opendata.arcgis.com/ (2018)"}}, {"type": "node", "id": 6557369378, "lat": 38.7476855, "lon": -90.5587841, "tags": {"addr:city": "Saint Peters", "addr:housenumber": "1316", "addr:postcode": "63303", "addr:street": "Magnolia Manor Court", "source:addr": "https://gis.sccmo.opendata.arcgis.com/ (2018)"}}, {"type": "node", "id": 6557369379, "lat": 38.7474725, "lon": -90.5600019, "tags": {"addr:city": "Saint Peters", "addr:housenumber": "1313", "addr:postcode": "63303", "addr:street": "Magnolia Manor Circle", "source:addr": "https://gis.sccmo.opendata.arcgis.com/ (2018)"}}, {"type": "node", "id": 6557369382, "lat": 38.7470448, "lon": -90.5598431, "tags": {"addr:city": "Saint Peters", "addr:housenumber": "1307", "addr:postcode": "63303", "addr:street": "Magnolia Manor Circle", "source:addr": "https://gis.sccmo.opendata.arcgis.com/ (2018)"}}, {"type": "node", "id": 6557369383, "lat": 38.7471006, "lon": -90.5601119, "tags": {"addr:city": "Saint Peters", "addr:housenumber": "1309", "addr:postcode": "63303", "addr:street": "Magnolia Manor Circle", "source:addr": "https://gis.sccmo.opendata.arcgis.com/ (2018)"}}, {"type": "node", "id": 6557369384, "lat": 38.7478326, "lon": -90.5588697, "tags": {"addr:city": "Saint Peters", "addr:housenumber": "1320", "addr:postcode": "63303", "addr:street": "Magnolia Manor Court", "source:addr": "https://gis.sccmo.opendata.arcgis.com/ (2018)"}}, {"type": "node", "id": 6557369396, "lat": 38.7475096, "lon": -90.5597826, "tags": {"addr:city": "Saint Peters", "addr:housenumber": "1315", "addr:postcode": "63303", "addr:street": "Magnolia Manor Circle", "source:addr": "https://gis.sccmo.opendata.arcgis.com/ (2018)"}}, {"type": "node", "id": 6557425575, "lat": 38.7483232, "lon": -90.5573964, "tags": {"addr:city": "Saint Peters", "addr:housenumber": "1531", "addr:postcode": "63303", "addr:street": "Heritage Manor Circle", "source:addr": "https://gis.sccmo.opendata.arcgis.com/ (2018)"}}, {"type": "node", "id": 6557448587, "lat": 38.7485584, "lon": -90.5572297, "tags": {"addr:city": "Saint Peters", "addr:housenumber": "1533", "addr:postcode": "63303", "addr:street": "Heritage Manor Circle", "source:addr": "https://gis.sccmo.opendata.arcgis.com/ (2018)"}}, {"type": "node", "id": 6557448591, "lat": 38.7481493, "lon": -90.5572464, "tags": {"addr:city": "Saint Peters", "addr:housenumber": "1529", "addr:postcode": "63303", "addr:street": "Heritage Manor Circle", "source:addr": "https://gis.sccmo.opendata.arcgis.com/ (2018)"}}]}